{
"meta":{"test_sets":[],"test_metrics":[],"learn_metrics":[{"best_value":"Min","name":"Logloss"}],"launch_mode":"Train","parameters":"","iteration_count":500,"learn_sets":["learn"],"name":"experiment"},
"iterations":[
{"learn":[0.4322459329],"iteration":0,"passed_time":0.0007445833938,"remaining_time":0.3715471135},
{"learn":[0.4023647063],"iteration":1,"passed_time":0.001674715257,"remaining_time":0.417004099},
{"learn":[0.3993102698],"iteration":2,"passed_time":0.0022700566,"remaining_time":0.37607271},
{"learn":[0.3974307827],"iteration":3,"passed_time":0.002706963619,"remaining_time":0.3356634888},
{"learn":[0.3766363807],"iteration":4,"passed_time":0.003467091063,"remaining_time":0.3432420152},
{"learn":[0.369662192],"iteration":5,"passed_time":0.004173198332,"remaining_time":0.3435933293},
{"learn":[0.3491322369],"iteration":6,"passed_time":0.004916671317,"remaining_time":0.3462741371},
{"learn":[0.3444398808],"iteration":7,"passed_time":0.005582557344,"remaining_time":0.3433272766},
{"learn":[0.3364263232],"iteration":8,"passed_time":0.006294219996,"remaining_time":0.3433846687},
{"learn":[0.3248001847],"iteration":9,"passed_time":0.006905229324,"remaining_time":0.3383562369},
{"learn":[0.3198243546],"iteration":10,"passed_time":0.007517236817,"remaining_time":0.3341753458},
{"learn":[0.3176751661],"iteration":11,"passed_time":0.00820999747,"remaining_time":0.3338732304},
{"learn":[0.3116745858],"iteration":12,"passed_time":0.009097935812,"remaining_time":0.3408226723},
{"learn":[0.3097529519],"iteration":13,"passed_time":0.01013090908,"remaining_time":0.3516872723},
{"learn":[0.3077985437],"iteration":14,"passed_time":0.01072418327,"remaining_time":0.3467485925},
{"learn":[0.3054678062],"iteration":15,"passed_time":0.01131411054,"remaining_time":0.3422518438},
{"learn":[0.3047772513],"iteration":16,"passed_time":0.01185863031,"remaining_time":0.3369246141},
{"learn":[0.3028608881],"iteration":17,"passed_time":0.01246318263,"remaining_time":0.3337363349},
{"learn":[0.2996462665],"iteration":18,"passed_time":0.01305525522,"remaining_time":0.3305040926},
{"learn":[0.2982124781],"iteration":19,"passed_time":0.01363301376,"remaining_time":0.3271923301},
{"learn":[0.2969225847],"iteration":20,"passed_time":0.01422331416,"remaining_time":0.3244270231},
{"learn":[0.2958292962],"iteration":21,"passed_time":0.01496231946,"remaining_time":0.3250903955},
{"learn":[0.294465458],"iteration":22,"passed_time":0.0158023883,"remaining_time":0.3277277922},
{"learn":[0.2935652821],"iteration":23,"passed_time":0.0165214156,"remaining_time":0.3276747426},
{"learn":[0.2921611903],"iteration":24,"passed_time":0.01724256516,"remaining_time":0.327608738},
{"learn":[0.2916796632],"iteration":25,"passed_time":0.01802782846,"remaining_time":0.3286611804},
{"learn":[0.2909983067],"iteration":26,"passed_time":0.01899167311,"remaining_time":0.3327059771},
{"learn":[0.2896537395],"iteration":27,"passed_time":0.01969755389,"remaining_time":0.3320444799},
{"learn":[0.2889638934],"iteration":28,"passed_time":0.02051935544,"remaining_time":0.333262635},
{"learn":[0.2882845881],"iteration":29,"passed_time":0.02150192872,"remaining_time":0.33686355},
{"learn":[0.2878144977],"iteration":30,"passed_time":0.02219644452,"remaining_time":0.3358107251},
{"learn":[0.2874365827],"iteration":31,"passed_time":0.02299855035,"remaining_time":0.3363537989},
{"learn":[0.2872514665],"iteration":32,"passed_time":0.0236569017,"remaining_time":0.3347810028},
{"learn":[0.2862961588],"iteration":33,"passed_time":0.02426071876,"remaining_time":0.3325145571},
{"learn":[0.2859962811],"iteration":34,"passed_time":0.02508669036,"remaining_time":0.3332946005},
{"learn":[0.2858443173],"iteration":35,"passed_time":0.02599194559,"remaining_time":0.3350072988},
{"learn":[0.2849782573],"iteration":36,"passed_time":0.02665003805,"remaining_time":0.3334856113},
{"learn":[0.2846647203],"iteration":37,"passed_time":0.02723501825,"remaining_time":0.331120485},
{"learn":[0.284300437],"iteration":38,"passed_time":0.02801588735,"remaining_time":0.3311621556},
{"learn":[0.2840014854],"iteration":39,"passed_time":0.02886147617,"remaining_time":0.3319069759},
{"learn":[0.2833594894],"iteration":40,"passed_time":0.02960985412,"remaining_time":0.3314859279},
{"learn":[0.2830084623],"iteration":41,"passed_time":0.03024601,"remaining_time":0.3298255376},
{"learn":[0.2824893386],"iteration":42,"passed_time":0.03092315678,"remaining_time":0.3286484337},
{"learn":[0.2822966289],"iteration":43,"passed_time":0.03163957575,"remaining_time":0.3279010578},
{"learn":[0.2819799132],"iteration":44,"passed_time":0.03240490147,"remaining_time":0.3276495593},
{"learn":[0.2816663215],"iteration":45,"passed_time":0.03305476641,"remaining_time":0.3262361729},
{"learn":[0.2815880402],"iteration":46,"passed_time":0.03370873693,"remaining_time":0.3248948474},
{"learn":[0.2813268841],"iteration":47,"passed_time":0.03435977241,"remaining_time":0.3235545235},
{"learn":[0.2811135485],"iteration":48,"passed_time":0.03514390158,"remaining_time":0.323467339},
{"learn":[0.2810311953],"iteration":49,"passed_time":0.03598096824,"remaining_time":0.3238287142},
{"learn":[0.2809416436],"iteration":50,"passed_time":0.036749077,"remaining_time":0.3235359916},
{"learn":[0.2807838808],"iteration":51,"passed_time":0.03736865959,"remaining_time":0.3219453749},
{"learn":[0.2806112035],"iteration":52,"passed_time":0.03819044244,"remaining_time":0.3220967504},
{"learn":[0.2803135633],"iteration":53,"passed_time":0.03886368509,"remaining_time":0.3209852509},
{"learn":[0.2801585226],"iteration":54,"passed_time":0.03949372102,"remaining_time":0.3195401064},
{"learn":[0.2799214631],"iteration":55,"passed_time":0.04049230937,"remaining_time":0.3210461671},
{"learn":[0.279768243],"iteration":56,"passed_time":0.04128521524,"remaining_time":0.3208657957},
{"learn":[0.2796619639],"iteration":57,"passed_time":0.04185252178,"remaining_time":0.3189450797},
{"learn":[0.279507336],"iteration":58,"passed_time":0.04268678837,"remaining_time":0.3190656554},
{"learn":[0.2792924772],"iteration":59,"passed_time":0.0433024725,"remaining_time":0.317551465},
{"learn":[0.2792481975],"iteration":60,"passed_time":0.04412487402,"remaining_time":0.3175544212},
{"learn":[0.2790751155],"iteration":61,"passed_time":0.04495567176,"remaining_time":0.3175900682},
{"learn":[0.278984567],"iteration":62,"passed_time":0.04562838292,"remaining_time":0.3165016403},
{"learn":[0.2789259964],"iteration":63,"passed_time":0.04640038011,"remaining_time":0.3161025895},
{"learn":[0.2788089985],"iteration":64,"passed_time":0.04726460334,"remaining_time":0.3163092685},
{"learn":[0.2786221925],"iteration":65,"passed_time":0.0479544901,"remaining_time":0.3153371015},
{"learn":[0.2785147127],"iteration":66,"passed_time":0.04863901656,"remaining_time":0.3143387189},
{"learn":[0.2783738909],"iteration":67,"passed_time":0.04932896812,"remaining_time":0.3133840327},
{"learn":[0.278286589],"iteration":68,"passed_time":0.04996155024,"remaining_time":0.3120786689},
{"learn":[0.2782351164],"iteration":69,"passed_time":0.05068701182,"remaining_time":0.3113630726},
{"learn":[0.2781431472],"iteration":70,"passed_time":0.05123324464,"remaining_time":0.3095642528},
{"learn":[0.2780735572],"iteration":71,"passed_time":0.05190407907,"remaining_time":0.3085409145},
{"learn":[0.2779845081],"iteration":72,"passed_time":0.05264409756,"remaining_time":0.3079319131},
{"learn":[0.277930865],"iteration":73,"passed_time":0.0532951424,"remaining_time":0.3068071711},
{"learn":[0.277903715],"iteration":74,"passed_time":0.05414203704,"remaining_time":0.3068048766},
{"learn":[0.2778556624],"iteration":75,"passed_time":0.05491514631,"remaining_time":0.306368711},
{"learn":[0.2778213154],"iteration":76,"passed_time":0.05566153863,"remaining_time":0.3057770239},
{"learn":[0.2777790802],"iteration":77,"passed_time":0.05642994069,"remaining_time":0.3053004483},
{"learn":[0.2777501155],"iteration":78,"passed_time":0.05713028913,"remaining_time":0.3044538193},
{"learn":[0.2777017893],"iteration":79,"passed_time":0.05781622365,"remaining_time":0.3035351741},
{"learn":[0.2776665564],"iteration":80,"passed_time":0.05843051175,"remaining_time":0.3022516596},
{"learn":[0.27763536],"iteration":81,"passed_time":0.05913124503,"remaining_time":0.3014251271},
{"learn":[0.2775875652],"iteration":82,"passed_time":0.05974042773,"remaining_time":0.300141667},
{"learn":[0.2775044265],"iteration":83,"passed_time":0.06048969061,"remaining_time":0.2995679916},
{"learn":[0.2774679972],"iteration":84,"passed_time":0.0614252763,"remaining_time":0.2998998784},
{"learn":[0.2774208497],"iteration":85,"passed_time":0.06210539453,"remaining_time":0.2989724807},
{"learn":[0.2773772377],"iteration":86,"passed_time":0.06277975928,"remaining_time":0.298023455},
{"learn":[0.2773070524],"iteration":87,"passed_time":0.06359795501,"remaining_time":0.2977540621},
{"learn":[0.2772529764],"iteration":88,"passed_time":0.06432989732,"remaining_time":0.2970740202},
{"learn":[0.2772164076],"iteration":89,"passed_time":0.06495683854,"remaining_time":0.2959144867},
{"learn":[0.2771898729],"iteration":90,"passed_time":0.06559768526,"remaining_time":0.2948291568},
{"learn":[0.2771444399],"iteration":91,"passed_time":0.06626363108,"remaining_time":0.2938647987},
{"learn":[0.2770764605],"iteration":92,"passed_time":0.06694295191,"remaining_time":0.2929653917},
{"learn":[0.2770018144],"iteration":93,"passed_time":0.06771719063,"remaining_time":0.2924806319},
{"learn":[0.2769515425],"iteration":94,"passed_time":0.06839652082,"remaining_time":0.2915851677},
{"learn":[0.2769234584],"iteration":95,"passed_time":0.06918744039,"remaining_time":0.2911638116},
{"learn":[0.2768938363],"iteration":96,"passed_time":0.06982188321,"remaining_time":0.2900847313},
{"learn":[0.2768493852],"iteration":97,"passed_time":0.07045792283,"remaining_time":0.2890212753},
{"learn":[0.2768283786],"iteration":98,"passed_time":0.0711483237,"remaining_time":0.2881866445},
{"learn":[0.2768071674],"iteration":99,"passed_time":0.0719746798,"remaining_time":0.2878987192},
{"learn":[0.2767867389],"iteration":100,"passed_time":0.07278888354,"remaining_time":0.2875521241},
{"learn":[0.2767686049],"iteration":101,"passed_time":0.07351532558,"remaining_time":0.2868539175},
{"learn":[0.2767502619],"iteration":102,"passed_time":0.07413116605,"remaining_time":0.2857288633},
{"learn":[0.2767369546],"iteration":103,"passed_time":0.07488406582,"remaining_time":0.2851354814},
{"learn":[0.2767171275],"iteration":104,"passed_time":0.07562482258,"remaining_time":0.2844933802},
{"learn":[0.2767001372],"iteration":105,"passed_time":0.07646077382,"remaining_time":0.2842032536},
{"learn":[0.2766633997],"iteration":106,"passed_time":0.07719439511,"remaining_time":0.2835270774},
{"learn":[0.2766134401],"iteration":107,"passed_time":0.07806536698,"remaining_time":0.283348369},
{"learn":[0.2765858323],"iteration":108,"passed_time":0.07867448621,"remaining_time":0.2822176524},
{"learn":[0.2765557583],"iteration":109,"passed_time":0.07934587718,"remaining_time":0.2813172009},
{"learn":[0.2765110835],"iteration":110,"passed_time":0.08024317482,"remaining_time":0.2812125676},
{"learn":[0.2764819319],"iteration":111,"passed_time":0.08103938653,"remaining_time":0.2807435891},
{"learn":[0.2764524713],"iteration":112,"passed_time":0.08172380375,"remaining_time":0.2798859474},
{"learn":[0.2764198171],"iteration":113,"passed_time":0.08244865735,"remaining_time":0.2791682609},
{"learn":[0.2763819327],"iteration":114,"passed_time":0.08317513714,"remaining_time":0.2784558939},
{"learn":[0.2763249328],"iteration":115,"passed_time":0.08389944255,"remaining_time":0.2777360857},
{"learn":[0.276271433],"iteration":116,"passed_time":0.08450965315,"remaining_time":0.2766427107},
{"learn":[0.2762568598],"iteration":117,"passed_time":0.0851126521,"remaining_time":0.2755341788},
{"learn":[0.2762287523],"iteration":118,"passed_time":0.0858495094,"remaining_time":0.274862715},
{"learn":[0.2762180877],"iteration":119,"passed_time":0.08659623077,"remaining_time":0.2742213974},
{"learn":[0.2761981268],"iteration":120,"passed_time":0.08730018771,"remaining_time":0.2734443896},
{"learn":[0.2761660124],"iteration":121,"passed_time":0.08798615462,"remaining_time":0.2726128397},
{"learn":[0.2761485559],"iteration":122,"passed_time":0.08862900067,"remaining_time":0.2716514899},
{"learn":[0.2761290278],"iteration":123,"passed_time":0.0893438489,"remaining_time":0.2709136064},
{"learn":[0.2760914786],"iteration":124,"passed_time":0.08997606523,"remaining_time":0.2699281957},
{"learn":[0.2760757989],"iteration":125,"passed_time":0.09064766832,"remaining_time":0.2690653012},
{"learn":[0.2760750223],"iteration":126,"passed_time":0.09143535956,"remaining_time":0.268546371},
{"learn":[0.2760698851],"iteration":127,"passed_time":0.09222987459,"remaining_time":0.268043073},
{"learn":[0.2760616775],"iteration":128,"passed_time":0.09308499708,"remaining_time":0.2677095653},
{"learn":[0.2760600875],"iteration":129,"passed_time":0.09381414767,"remaining_time":0.2670094972},
{"learn":[0.2760477118],"iteration":130,"passed_time":0.09449948155,"remaining_time":0.2661855625},
{"learn":[0.2760327661],"iteration":131,"passed_time":0.09533032237,"remaining_time":0.2657693836},
{"learn":[0.2760167982],"iteration":132,"passed_time":0.09600102318,"remaining_time":0.264905079},
{"learn":[0.2759513252],"iteration":133,"passed_time":0.09658786141,"remaining_time":0.2638146065},
{"learn":[0.2759145179],"iteration":134,"passed_time":0.09744499994,"remaining_time":0.2634624073},
{"learn":[0.27588025],"iteration":135,"passed_time":0.09828901334,"remaining_time":0.2630676534},
{"learn":[0.2758579425],"iteration":136,"passed_time":0.09904231799,"remaining_time":0.2624259958},
{"learn":[0.2758378118],"iteration":137,"passed_time":0.09970236802,"remaining_time":0.2615380958},
{"learn":[0.2758099313],"iteration":138,"passed_time":0.1004143243,"remaining_time":0.2607882811},
{"learn":[0.2757961133],"iteration":139,"passed_time":0.1012304646,"remaining_time":0.2603069089},
{"learn":[0.275757767],"iteration":140,"passed_time":0.1018770832,"remaining_time":0.2593891692},
{"learn":[0.2757266212],"iteration":141,"passed_time":0.1025943733,"remaining_time":0.2586534201},
{"learn":[0.2757157491],"iteration":142,"passed_time":0.1032595358,"remaining_time":0.2577877922},
{"learn":[0.2756956008],"iteration":143,"passed_time":0.1041836947,"remaining_time":0.2575652452},
{"learn":[0.2756954824],"iteration":144,"passed_time":0.1046037846,"remaining_time":0.2560989209},
{"learn":[0.2756825723],"iteration":145,"passed_time":0.1053987536,"remaining_time":0.255555882},
{"learn":[0.2756628148],"iteration":146,"passed_time":0.106002576,"remaining_time":0.2545504036},
{"learn":[0.2756513531],"iteration":147,"passed_time":0.1067288781,"remaining_time":0.253841656},
{"learn":[0.2756453428],"iteration":148,"passed_time":0.1075315632,"remaining_time":0.2533126085},
{"learn":[0.2756273104],"iteration":149,"passed_time":0.1081326483,"remaining_time":0.2523095127},
{"learn":[0.2756127978],"iteration":150,"passed_time":0.1090012641,"remaining_time":0.2519300739},
{"learn":[0.2756130557],"iteration":151,"passed_time":0.109531698,"remaining_time":0.25076994},
{"learn":[0.2756128821],"iteration":152,"passed_time":0.1100707191,"remaining_time":0.2496375133},
{"learn":[0.2756126215],"iteration":153,"passed_time":0.1107142774,"remaining_time":0.2487476622},
{"learn":[0.2755936227],"iteration":154,"passed_time":0.1114680273,"remaining_time":0.2481062544},
{"learn":[0.2755929081],"iteration":155,"passed_time":0.1120805022,"remaining_time":0.2471518766},
{"learn":[0.275574394],"iteration":156,"passed_time":0.1128817919,"remaining_time":0.2466143607},
{"learn":[0.2755607968],"iteration":157,"passed_time":0.113591958,"remaining_time":0.2458762635},
{"learn":[0.2755453402],"iteration":158,"passed_time":0.1143074837,"remaining_time":0.2451500122},
{"learn":[0.2755323217],"iteration":159,"passed_time":0.1150240403,"remaining_time":0.2444260856},
{"learn":[0.2755277294],"iteration":160,"passed_time":0.1158883193,"remaining_time":0.2440132934},
{"learn":[0.2755224143],"iteration":161,"passed_time":0.1166512902,"remaining_time":0.2433835562},
{"learn":[0.2755133575],"iteration":162,"passed_time":0.1173910969,"remaining_time":0.2427042925},
{"learn":[0.2754846301],"iteration":163,"passed_time":0.1180902488,"remaining_time":0.2419409975},
{"learn":[0.2754740595],"iteration":164,"passed_time":0.1187043976,"remaining_time":0.2410058982},
{"learn":[0.2754741963],"iteration":165,"passed_time":0.1192627961,"remaining_time":0.2399624934},
{"learn":[0.2754688806],"iteration":166,"passed_time":0.1202708036,"remaining_time":0.2398214227},
{"learn":[0.2754616534],"iteration":167,"passed_time":0.1210300301,"remaining_time":0.2391783928},
{"learn":[0.2754504195],"iteration":168,"passed_time":0.1217381467,"remaining_time":0.238433885},
{"learn":[0.2754504195],"iteration":169,"passed_time":0.1222926107,"remaining_time":0.2373915385},
{"learn":[0.2754504195],"iteration":170,"passed_time":0.1227975967,"remaining_time":0.2362597037},
{"learn":[0.2754504195],"iteration":171,"passed_time":0.1233809578,"remaining_time":0.2352846171},
{"learn":[0.2754504667],"iteration":172,"passed_time":0.1238835179,"remaining_time":0.2341613314},
{"learn":[0.2754507056],"iteration":173,"passed_time":0.1243938956,"remaining_time":0.2330598273},
{"learn":[0.2754505627],"iteration":174,"passed_time":0.1249694159,"remaining_time":0.2320860581},
{"learn":[0.2754505393],"iteration":175,"passed_time":0.1255482338,"remaining_time":0.2311228849},
{"learn":[0.2754507389],"iteration":176,"passed_time":0.126120493,"remaining_time":0.2301520862},
{"learn":[0.2754507389],"iteration":177,"passed_time":0.1270536334,"remaining_time":0.2298385953},
{"learn":[0.2754441335],"iteration":178,"passed_time":0.1276771171,"remaining_time":0.2289628749},
{"learn":[0.2754298507],"iteration":179,"passed_time":0.1284833162,"remaining_time":0.2284147843},
{"learn":[0.2754108784],"iteration":180,"passed_time":0.1293196128,"remaining_time":0.2279168867},
{"learn":[0.2753959527],"iteration":181,"passed_time":0.1301481473,"remaining_time":0.227401708},
{"learn":[0.2753798724],"iteration":182,"passed_time":0.1309247024,"remaining_time":0.2267930637},
{"learn":[0.2753642819],"iteration":183,"passed_time":0.1315966633,"remaining_time":0.2260029652},
{"learn":[0.2753635573],"iteration":184,"passed_time":0.1322225823,"remaining_time":0.2251357482},
{"learn":[0.2753483475],"iteration":185,"passed_time":0.1329836728,"remaining_time":0.2244993186},
{"learn":[0.2753451258],"iteration":186,"passed_time":0.1337106293,"remaining_time":0.2238044223},
{"learn":[0.2753223924],"iteration":187,"passed_time":0.1344952632,"remaining_time":0.223204905},
{"learn":[0.2753134369],"iteration":188,"passed_time":0.1352866675,"remaining_time":0.2226145693},
{"learn":[0.2753137841],"iteration":189,"passed_time":0.1358402469,"remaining_time":0.2216340871},
{"learn":[0.2753020703],"iteration":190,"passed_time":0.1365680984,"remaining_time":0.2209400126},
{"learn":[0.2752983829],"iteration":191,"passed_time":0.1372612512,"remaining_time":0.2201899238},
{"learn":[0.2752891317],"iteration":192,"passed_time":0.1380991337,"remaining_time":0.2196706427},
{"learn":[0.2752741252],"iteration":193,"passed_time":0.1389128807,"remaining_time":0.2191100078},
{"learn":[0.2752655509],"iteration":194,"passed_time":0.1395026092,"remaining_time":0.2181963888},
{"learn":[0.2752540096],"iteration":195,"passed_time":0.1402330403,"remaining_time":0.2175043074},
{"learn":[0.275245973],"iteration":196,"passed_time":0.1408158932,"remaining_time":0.2165848509},
{"learn":[0.2752433003],"iteration":197,"passed_time":0.1414721904,"remaining_time":0.2157808157},
{"learn":[0.2752324661],"iteration":198,"passed_time":0.1422679752,"remaining_time":0.2151892489},
{"learn":[0.2752164955],"iteration":199,"passed_time":0.1431626929,"remaining_time":0.2147440394},
{"learn":[0.2751967714],"iteration":200,"passed_time":0.1438810544,"remaining_time":0.2140320163},
{"learn":[0.2751874812],"iteration":201,"passed_time":0.1446609949,"remaining_time":0.2134107746},
{"learn":[0.2751762501],"iteration":202,"passed_time":0.1453495544,"remaining_time":0.2126542742},
{"learn":[0.2751720814],"iteration":203,"passed_time":0.1460491515,"remaining_time":0.2119144552},
{"learn":[0.2751596885],"iteration":204,"passed_time":0.1467703268,"remaining_time":0.2112060801},
{"learn":[0.2751547466],"iteration":205,"passed_time":0.1474327574,"remaining_time":0.2104137411},
{"learn":[0.2751464155],"iteration":206,"passed_time":0.1481506535,"remaining_time":0.2097011666},
{"learn":[0.2751353386],"iteration":207,"passed_time":0.1488467705,"remaining_time":0.2089579662},
{"learn":[0.2751189492],"iteration":208,"passed_time":0.1495864098,"remaining_time":0.2082758146},
{"learn":[0.2751143088],"iteration":209,"passed_time":0.1503007473,"remaining_time":0.2075581748},
{"learn":[0.2751142511],"iteration":210,"passed_time":0.1508918892,"remaining_time":0.2066718292},
{"learn":[0.2751086391],"iteration":211,"passed_time":0.1515534241,"remaining_time":0.2058838969},
{"learn":[0.2751015756],"iteration":212,"passed_time":0.1521648456,"remaining_time":0.2050296277},
{"learn":[0.275096093],"iteration":213,"passed_time":0.1528739738,"remaining_time":0.204308208},
{"learn":[0.2750847194],"iteration":214,"passed_time":0.1540266848,"remaining_time":0.2041749077},
{"learn":[0.2750787812],"iteration":215,"passed_time":0.1547417732,"remaining_time":0.2034567759},
{"learn":[0.2750787812],"iteration":216,"passed_time":0.155312275,"remaining_time":0.2025501098},
{"learn":[0.2750664193],"iteration":217,"passed_time":0.1559491561,"remaining_time":0.2017323946},
{"learn":[0.2750578615],"iteration":218,"passed_time":0.1566665074,"remaining_time":0.2010195826},
{"learn":[0.2750479814],"iteration":219,"passed_time":0.1574970556,"remaining_time":0.2004507981},
{"learn":[0.2750375825],"iteration":220,"passed_time":0.1581660167,"remaining_time":0.19967565},
{"learn":[0.2750357365],"iteration":221,"passed_time":0.1587957112,"remaining_time":0.198852287},
{"learn":[0.2750296898],"iteration":222,"passed_time":0.1594515855,"remaining_time":0.1980631802},
{"learn":[0.2750295858],"iteration":223,"passed_time":0.1600700887,"remaining_time":0.1972292165},
{"learn":[0.2750228514],"iteration":224,"passed_time":0.160833076,"remaining_time":0.1965737596},
{"learn":[0.2750223414],"iteration":225,"passed_time":0.161502154,"remaining_time":0.1958034964},
{"learn":[0.275017512],"iteration":226,"passed_time":0.1622788768,"remaining_time":0.1951635831},
{"learn":[0.2750108264],"iteration":227,"passed_time":0.1629200021,"remaining_time":0.1943607042},
{"learn":[0.2750002521],"iteration":228,"passed_time":0.1636850435,"remaining_time":0.1937058812},
{"learn":[0.274993249],"iteration":229,"passed_time":0.1645868429,"remaining_time":0.1932106417},
{"learn":[0.2749931732],"iteration":230,"passed_time":0.1654282781,"remaining_time":0.1926415879},
{"learn":[0.2749931403],"iteration":231,"passed_time":0.1660119722,"remaining_time":0.1917724506},
{"learn":[0.2749927846],"iteration":232,"passed_time":0.166606801,"remaining_time":0.1909185231},
{"learn":[0.2749917561],"iteration":233,"passed_time":0.1673496039,"remaining_time":0.1902350198},
{"learn":[0.2749915237],"iteration":234,"passed_time":0.1681077731,"remaining_time":0.1895683399},
{"learn":[0.2749916508],"iteration":235,"passed_time":0.1688105953,"remaining_time":0.188838971},
{"learn":[0.2749875141],"iteration":236,"passed_time":0.1695787995,"remaining_time":0.1881823809},
{"learn":[0.274979297],"iteration":237,"passed_time":0.1704031359,"remaining_time":0.1875866454},
{"learn":[0.2749670058],"iteration":238,"passed_time":0.1711441202,"remaining_time":0.1868979723},
{"learn":[0.274956082],"iteration":239,"passed_time":0.1718545204,"remaining_time":0.1861757305},
{"learn":[0.2749560441],"iteration":240,"passed_time":0.1725150184,"remaining_time":0.1853999576},
{"learn":[0.2749524683],"iteration":241,"passed_time":0.173593616,"remaining_time":0.1850708799},
{"learn":[0.2749522042],"iteration":242,"passed_time":0.174272997,"remaining_time":0.1843134165},
{"learn":[0.2749523475],"iteration":243,"passed_time":0.1747992391,"remaining_time":0.183395923},
{"learn":[0.2749500754],"iteration":244,"passed_time":0.175417253,"remaining_time":0.1825771408},
{"learn":[0.2749483975],"iteration":245,"passed_time":0.1762522287,"remaining_time":0.1819840085},
{"learn":[0.2749479516],"iteration":246,"passed_time":0.1768677562,"remaining_time":0.181164139},
{"learn":[0.2749410582],"iteration":247,"passed_time":0.1777258508,"remaining_time":0.1805923968},
{"learn":[0.2749253873],"iteration":248,"passed_time":0.1784702258,"remaining_time":0.1799037215},
{"learn":[0.2749138158],"iteration":249,"passed_time":0.1790365725,"remaining_time":0.1790365725},
{"learn":[0.2749067775],"iteration":250,"passed_time":0.1804024269,"remaining_time":0.1789649573},
{"learn":[0.2748907212],"iteration":251,"passed_time":0.1811342826,"remaining_time":0.1782591353},
{"learn":[0.2748877378],"iteration":252,"passed_time":0.1817194903,"remaining_time":0.1774099372},
{"learn":[0.2748871665],"iteration":253,"passed_time":0.1823350048,"remaining_time":0.17659217},
{"learn":[0.2748838103],"iteration":254,"passed_time":0.1830473639,"remaining_time":0.1758690359},
{"learn":[0.2748837767],"iteration":255,"passed_time":0.183624457,"remaining_time":0.1750170606},
{"learn":[0.2748818385],"iteration":256,"passed_time":0.18419302,"remaining_time":0.1741591589},
{"learn":[0.2748800039],"iteration":257,"passed_time":0.1847947301,"remaining_time":0.1733345918},
{"learn":[0.2748796748],"iteration":258,"passed_time":0.1854222713,"remaining_time":0.1725357814},
{"learn":[0.2748790769],"iteration":259,"passed_time":0.1860817908,"remaining_time":0.1717678069},
{"learn":[0.2748774186],"iteration":260,"passed_time":0.1866554792,"remaining_time":0.1709220672},
{"learn":[0.2748774222],"iteration":261,"passed_time":0.1872289966,"remaining_time":0.1700782488},
{"learn":[0.274872698],"iteration":262,"passed_time":0.1879669192,"remaining_time":0.1693846382},
{"learn":[0.2748629034],"iteration":263,"passed_time":0.1887715401,"remaining_time":0.1687503162},
{"learn":[0.2748568728],"iteration":264,"passed_time":0.1894114371,"remaining_time":0.1679686329},
{"learn":[0.2748530593],"iteration":265,"passed_time":0.1901473297,"remaining_time":0.1672724629},
{"learn":[0.2748527905],"iteration":266,"passed_time":0.1909733407,"remaining_time":0.1666546381},
{"learn":[0.2748529738],"iteration":267,"passed_time":0.191486455,"remaining_time":0.1657643939},
{"learn":[0.2748517807],"iteration":268,"passed_time":0.1919807512,"remaining_time":0.1648607937},
{"learn":[0.2748516863],"iteration":269,"passed_time":0.1925739201,"remaining_time":0.1640444505},
{"learn":[0.2748517817],"iteration":270,"passed_time":0.1932954846,"remaining_time":0.1633382508},
{"learn":[0.2748519845],"iteration":271,"passed_time":0.1939598891,"remaining_time":0.1625840247},
{"learn":[0.2748519172],"iteration":272,"passed_time":0.1946035746,"remaining_time":0.1618132287},
{"learn":[0.2748520226],"iteration":273,"passed_time":0.1952163578,"remaining_time":0.1610178717},
{"learn":[0.2748483692],"iteration":274,"passed_time":0.1959236179,"remaining_time":0.1603011419},
{"learn":[0.2748418729],"iteration":275,"passed_time":0.196686669,"remaining_time":0.1596297604},
{"learn":[0.2748390158],"iteration":276,"passed_time":0.197276772,"remaining_time":0.1588184843},
{"learn":[0.2748386472],"iteration":277,"passed_time":0.1977636982,"remaining_time":0.1579264064},
{"learn":[0.2748384193],"iteration":278,"passed_time":0.1983347278,"remaining_time":0.1571038525},
{"learn":[0.2748254315],"iteration":279,"passed_time":0.199027116,"remaining_time":0.1563784482},
{"learn":[0.2748184777],"iteration":280,"passed_time":0.1996929499,"remaining_time":0.1556325837},
{"learn":[0.2748161768],"iteration":281,"passed_time":0.2004280965,"remaining_time":0.1549408689},
{"learn":[0.2748138746],"iteration":282,"passed_time":0.2013127099,"remaining_time":0.154363456},
{"learn":[0.2748120144],"iteration":283,"passed_time":0.2020541438,"remaining_time":0.1536749826},
{"learn":[0.2748089496],"iteration":284,"passed_time":0.2027321284,"remaining_time":0.1529382723},
{"learn":[0.2748076006],"iteration":285,"passed_time":0.2034210441,"remaining_time":0.1522101519},
{"learn":[0.2748047238],"iteration":286,"passed_time":0.2040657451,"remaining_time":0.1514494903},
{"learn":[0.2748048545],"iteration":287,"passed_time":0.20480871,"remaining_time":0.1507619671},
{"learn":[0.2748048545],"iteration":288,"passed_time":0.2053832963,"remaining_time":0.1499511264},
{"learn":[0.274804967],"iteration":289,"passed_time":0.2060331252,"remaining_time":0.149196401},
{"learn":[0.2748040686],"iteration":290,"passed_time":0.206582581,"remaining_time":0.1483703073},
{"learn":[0.2747963172],"iteration":291,"passed_time":0.2074316377,"remaining_time":0.1477595227},
{"learn":[0.2747947878],"iteration":292,"passed_time":0.2082495679,"remaining_time":0.1471251213},
{"learn":[0.2747949007],"iteration":293,"passed_time":0.2089169558,"remaining_time":0.1463839894},
{"learn":[0.2747947203],"iteration":294,"passed_time":0.2095177199,"remaining_time":0.1455970596},
{"learn":[0.2747912135],"iteration":295,"passed_time":0.2101700966,"remaining_time":0.1448469585},
{"learn":[0.2747912943],"iteration":296,"passed_time":0.2107699795,"remaining_time":0.1440616358},
{"learn":[0.2747912698],"iteration":297,"passed_time":0.2113564686,"remaining_time":0.1432684787},
{"learn":[0.2747893073],"iteration":298,"passed_time":0.2120060613,"remaining_time":0.1425191248},
{"learn":[0.2747853883],"iteration":299,"passed_time":0.2126703125,"remaining_time":0.1417802083},
{"learn":[0.2747825883],"iteration":300,"passed_time":0.2132363696,"remaining_time":0.140976869},
{"learn":[0.2747825457],"iteration":301,"passed_time":0.2142459431,"remaining_time":0.1404658832},
{"learn":[0.2747821584],"iteration":302,"passed_time":0.214888387,"remaining_time":0.1397129117},
{"learn":[0.2747817631],"iteration":303,"passed_time":0.2155797787,"remaining_time":0.1389922257},
{"learn":[0.274781487],"iteration":304,"passed_time":0.2162167703,"remaining_time":0.1382369515},
{"learn":[0.2747812347],"iteration":305,"passed_time":0.2167717248,"remaining_time":0.1374304399},
{"learn":[0.2747705964],"iteration":306,"passed_time":0.2173606188,"remaining_time":0.1366469037},
{"learn":[0.2747623857],"iteration":307,"passed_time":0.2180824411,"remaining_time":0.1359474958},
{"learn":[0.2747577433],"iteration":308,"passed_time":0.2187366462,"remaining_time":0.135206147},
{"learn":[0.2747511687],"iteration":309,"passed_time":0.2194120228,"remaining_time":0.1344783365},
{"learn":[0.2747430267],"iteration":310,"passed_time":0.2200811852,"remaining_time":0.1337470868},
{"learn":[0.2747399581],"iteration":311,"passed_time":0.2206974914,"remaining_time":0.1329843858},
{"learn":[0.2747344584],"iteration":312,"passed_time":0.2214118445,"remaining_time":0.1322811979},
{"learn":[0.2747288384],"iteration":313,"passed_time":0.2222045129,"remaining_time":0.1316243293},
{"learn":[0.274727056],"iteration":314,"passed_time":0.2229601282,"remaining_time":0.1309448372},
{"learn":[0.2747275174],"iteration":315,"passed_time":0.2234896378,"remaining_time":0.1301332068},
{"learn":[0.2747273572],"iteration":316,"passed_time":0.2241585126,"remaining_time":0.1294038101},
{"learn":[0.2747272929],"iteration":317,"passed_time":0.2246791673,"remaining_time":0.1285899637},
{"learn":[0.2747264329],"iteration":318,"passed_time":0.2252488336,"remaining_time":0.1278057645},
{"learn":[0.2747265367],"iteration":319,"passed_time":0.2257691723,"remaining_time":0.1269951594},
{"learn":[0.2747242167],"iteration":320,"passed_time":0.2262869634,"remaining_time":0.1261849422},
{"learn":[0.2747195064],"iteration":321,"passed_time":0.2272147027,"remaining_time":0.1256031587},
{"learn":[0.2747118983],"iteration":322,"passed_time":0.2280698493,"remaining_time":0.124979453},
{"learn":[0.2747045336],"iteration":323,"passed_time":0.2288045953,"remaining_time":0.124288916},
{"learn":[0.274700611],"iteration":324,"passed_time":0.2293722433,"remaining_time":0.123508131},
{"learn":[0.2746964979],"iteration":325,"passed_time":0.2302321655,"remaining_time":0.1228846528},
{"learn":[0.2746915714],"iteration":326,"passed_time":0.2309258438,"remaining_time":0.1221717767},
{"learn":[0.2746880643],"iteration":327,"passed_time":0.2316882118,"remaining_time":0.1214950379},
{"learn":[0.274684388],"iteration":328,"passed_time":0.2323770062,"remaining_time":0.1207795382},
{"learn":[0.2746798786],"iteration":329,"passed_time":0.2330355907,"remaining_time":0.1200486376},
{"learn":[0.2746781346],"iteration":330,"passed_time":0.2339386836,"remaining_time":0.1194430137},
{"learn":[0.2746732179],"iteration":331,"passed_time":0.2347494963,"remaining_time":0.1187889017},
{"learn":[0.2746713867],"iteration":332,"passed_time":0.2354598304,"remaining_time":0.1180834585},
{"learn":[0.274669806],"iteration":333,"passed_time":0.2361418564,"remaining_time":0.1173639167},
{"learn":[0.2746697387],"iteration":334,"passed_time":0.2367634921,"remaining_time":0.1166148543},
{"learn":[0.2746697481],"iteration":335,"passed_time":0.2374513622,"remaining_time":0.1158988792},
{"learn":[0.2746696702],"iteration":336,"passed_time":0.2379681762,"remaining_time":0.1151003345},
{"learn":[0.2746690857],"iteration":337,"passed_time":0.2386567668,"remaining_time":0.1143857876},
{"learn":[0.2746693322],"iteration":338,"passed_time":0.2392320984,"remaining_time":0.1136176043},
{"learn":[0.2746659291],"iteration":339,"passed_time":0.2400188787,"remaining_time":0.1129500606},
{"learn":[0.2746610429],"iteration":340,"passed_time":0.2406796894,"remaining_time":0.112223081},
{"learn":[0.2746555642],"iteration":341,"passed_time":0.2413496679,"remaining_time":0.1115007238},
{"learn":[0.2746513143],"iteration":342,"passed_time":0.2419625039,"remaining_time":0.1107525164},
{"learn":[0.2746515291],"iteration":343,"passed_time":0.2426948988,"remaining_time":0.1100593146},
{"learn":[0.2746515989],"iteration":344,"passed_time":0.2433638482,"remaining_time":0.1093373811},
{"learn":[0.2746513563],"iteration":345,"passed_time":0.2438782343,"remaining_time":0.1085469598},
{"learn":[0.2746512068],"iteration":346,"passed_time":0.244545372,"remaining_time":0.107825481},
{"learn":[0.2746512068],"iteration":347,"passed_time":0.2450363917,"remaining_time":0.1070273895},
{"learn":[0.2746512068],"iteration":348,"passed_time":0.2455621431,"remaining_time":0.1062460848},
{"learn":[0.2746512068],"iteration":349,"passed_time":0.246117471,"remaining_time":0.1054789161},
{"learn":[0.2746512068],"iteration":350,"passed_time":0.2467119294,"remaining_time":0.1047295655},
{"learn":[0.2746510682],"iteration":351,"passed_time":0.2472774962,"remaining_time":0.1039689473},
{"learn":[0.2746510682],"iteration":352,"passed_time":0.2478737893,"remaining_time":0.1032222295},
{"learn":[0.2746510914],"iteration":353,"passed_time":0.2484395715,"remaining_time":0.1024637781},
{"learn":[0.2746509257],"iteration":354,"passed_time":0.2490110087,"remaining_time":0.1017087218},
{"learn":[0.2746509257],"iteration":355,"passed_time":0.2495153713,"remaining_time":0.1009275659},
{"learn":[0.2746509257],"iteration":356,"passed_time":0.2500196124,"remaining_time":0.100147912},
{"learn":[0.2746509257],"iteration":357,"passed_time":0.2506196072,"remaining_time":0.09940777714},
{"learn":[0.2746509257],"iteration":358,"passed_time":0.2511949361,"remaining_time":0.09865873535},
{"learn":[0.2746509257],"iteration":359,"passed_time":0.2517241774,"remaining_time":0.09789273565},
{"learn":[0.2746509257],"iteration":360,"passed_time":0.2523324257,"remaining_time":0.09715846864},
{"learn":[0.2746509257],"iteration":361,"passed_time":0.2528615097,"remaining_time":0.09639471917},
{"learn":[0.2746509257],"iteration":362,"passed_time":0.253456087,"remaining_time":0.09565698051},
{"learn":[0.2746509257],"iteration":363,"passed_time":0.2540438894,"remaining_time":0.09491749713},
{"learn":[0.2746509257],"iteration":364,"passed_time":0.2545670358,"remaining_time":0.09415493104},
{"learn":[0.2746509257],"iteration":365,"passed_time":0.255086868,"remaining_time":0.09339245987},
{"learn":[0.2746509257],"iteration":366,"passed_time":0.255689265,"remaining_time":0.09266123227},
{"learn":[0.2746509257],"iteration":367,"passed_time":0.2563127036,"remaining_time":0.09193825238},
{"learn":[0.2746509257],"iteration":368,"passed_time":0.2569957532,"remaining_time":0.09123697471},
{"learn":[0.2746509257],"iteration":369,"passed_time":0.2577333387,"remaining_time":0.09055495686},
{"learn":[0.2746509257],"iteration":370,"passed_time":0.2584654705,"remaining_time":0.0898707431},
{"learn":[0.2746509257],"iteration":371,"passed_time":0.2591441365,"remaining_time":0.08916787494},
{"learn":[0.2746509257],"iteration":372,"passed_time":0.2597325074,"remaining_time":0.08843439261},
{"learn":[0.2746509257],"iteration":373,"passed_time":0.2602947333,"remaining_time":0.08769287806},
{"learn":[0.2746509257],"iteration":374,"passed_time":0.2608649956,"remaining_time":0.08695499852},
{"learn":[0.2746509257],"iteration":375,"passed_time":0.261420873,"remaining_time":0.08621326662},
{"learn":[0.2746509257],"iteration":376,"passed_time":0.2620239564,"remaining_time":0.08548792213},
{"learn":[0.2746509257],"iteration":377,"passed_time":0.2625858065,"remaining_time":0.08474991637},
{"learn":[0.2746509257],"iteration":378,"passed_time":0.2631487094,"remaining_time":0.08401317637},
{"learn":[0.2746509257],"iteration":379,"passed_time":0.2636182994,"remaining_time":0.08324788401},
{"learn":[0.2746509257],"iteration":380,"passed_time":0.2641648011,"remaining_time":0.08250816622},
{"learn":[0.2746509257],"iteration":381,"passed_time":0.2646600567,"remaining_time":0.08175363007},
{"learn":[0.2746509257],"iteration":382,"passed_time":0.2651868837,"remaining_time":0.08101009242},
{"learn":[0.2746509257],"iteration":383,"passed_time":0.2657567391,"remaining_time":0.08028068161},
{"learn":[0.2746509257],"iteration":384,"passed_time":0.2663118439,"remaining_time":0.07954769362},
{"learn":[0.2746509257],"iteration":385,"passed_time":0.2668095461,"remaining_time":0.07879867423},
{"learn":[0.2746509257],"iteration":386,"passed_time":0.2673343708,"remaining_time":0.07805887313},
{"learn":[0.2746509257],"iteration":387,"passed_time":0.2680418213,"remaining_time":0.07737289688},
{"learn":[0.2746509257],"iteration":388,"passed_time":0.2685826371,"remaining_time":0.07663926148},
{"learn":[0.2746509257],"iteration":389,"passed_time":0.2690917718,"remaining_time":0.07589767921},
{"learn":[0.2746509257],"iteration":390,"passed_time":0.2696035288,"remaining_time":0.07515801698},
{"learn":[0.2746509257],"iteration":391,"passed_time":0.2700885839,"remaining_time":0.07441216088},
{"learn":[0.2746509257],"iteration":392,"passed_time":0.2706802306,"remaining_time":0.07369665311},
{"learn":[0.2746509257],"iteration":393,"passed_time":0.2712515963,"remaining_time":0.07297631777},
{"learn":[0.2746509257],"iteration":394,"passed_time":0.2717694408,"remaining_time":0.07224250959},
{"learn":[0.2746509257],"iteration":395,"passed_time":0.2722672299,"remaining_time":0.07150452503},
{"learn":[0.2746509257],"iteration":396,"passed_time":0.2727921729,"remaining_time":0.07077479548},
{"learn":[0.2746509257],"iteration":397,"passed_time":0.2733791016,"remaining_time":0.07006198082},
{"learn":[0.2746509257],"iteration":398,"passed_time":0.2739992929,"remaining_time":0.069358217},
{"learn":[0.2746509257],"iteration":399,"passed_time":0.2744799197,"remaining_time":0.06861997994},
{"learn":[0.2746509257],"iteration":400,"passed_time":0.2750673446,"remaining_time":0.0679093943},
{"learn":[0.2746509257],"iteration":401,"passed_time":0.2755658886,"remaining_time":0.06717775394},
{"learn":[0.2746509257],"iteration":402,"passed_time":0.2760492905,"remaining_time":0.06644362575},
{"learn":[0.2746509257],"iteration":403,"passed_time":0.2765298702,"remaining_time":0.06571006818},
{"learn":[0.2746509257],"iteration":404,"passed_time":0.277062065,"remaining_time":0.06498986709},
{"learn":[0.2746509257],"iteration":405,"passed_time":0.2775653824,"remaining_time":0.06426390626},
{"learn":[0.2746509257],"iteration":406,"passed_time":0.2782126948,"remaining_time":0.06357194254},
{"learn":[0.2746509257],"iteration":407,"passed_time":0.2787968839,"remaining_time":0.06286596402},
{"learn":[0.2746509257],"iteration":408,"passed_time":0.2794178949,"remaining_time":0.06216877369},
{"learn":[0.2746509257],"iteration":409,"passed_time":0.2799663476,"remaining_time":0.06145602752},
{"learn":[0.2746509257],"iteration":410,"passed_time":0.2804981534,"remaining_time":0.06074047605},
{"learn":[0.2746509257],"iteration":411,"passed_time":0.2809796525,"remaining_time":0.06001507141},
{"learn":[0.2746509257],"iteration":412,"passed_time":0.2815566267,"remaining_time":0.0593109601},
{"learn":[0.2746509257],"iteration":413,"passed_time":0.2820355328,"remaining_time":0.05858709135},
{"learn":[0.2746509257],"iteration":414,"passed_time":0.2824727418,"remaining_time":0.05785586278},
{"learn":[0.2746509257],"iteration":415,"passed_time":0.2829649421,"remaining_time":0.05713715177},
{"learn":[0.2746509257],"iteration":416,"passed_time":0.2835838004,"remaining_time":0.05644473726},
{"learn":[0.2746509257],"iteration":417,"passed_time":0.28416942,"remaining_time":0.05574615417},
{"learn":[0.2746509257],"iteration":418,"passed_time":0.2846666613,"remaining_time":0.05503102521},
{"learn":[0.2746509257],"iteration":419,"passed_time":0.2851423978,"remaining_time":0.05431283768},
{"learn":[0.2746509257],"iteration":420,"passed_time":0.2856135251,"remaining_time":0.05359493701},
{"learn":[0.2746509257],"iteration":421,"passed_time":0.286071598,"remaining_time":0.052875793},
{"learn":[0.2746509257],"iteration":422,"passed_time":0.2866181322,"remaining_time":0.05217398623},
{"learn":[0.2746509257],"iteration":423,"passed_time":0.2871497165,"remaining_time":0.05147023221},
{"learn":[0.2746509257],"iteration":424,"passed_time":0.2877185941,"remaining_time":0.05077386956},
{"learn":[0.2746509257],"iteration":425,"passed_time":0.2883203434,"remaining_time":0.05008381552},
{"learn":[0.2746509257],"iteration":426,"passed_time":0.2888390525,"remaining_time":0.04937997853},
{"learn":[0.2746509257],"iteration":427,"passed_time":0.2892944289,"remaining_time":0.04866635253},
{"learn":[0.2746509257],"iteration":428,"passed_time":0.2897334532,"remaining_time":0.04795122419},
{"learn":[0.2746509257],"iteration":429,"passed_time":0.290330241,"remaining_time":0.04726306249},
{"learn":[0.2746507835],"iteration":430,"passed_time":0.290845946,"remaining_time":0.04656234402},
{"learn":[0.2746507835],"iteration":431,"passed_time":0.291442667,"remaining_time":0.04587523461},
{"learn":[0.2746507835],"iteration":432,"passed_time":0.2919548339,"remaining_time":0.04517545928},
{"learn":[0.2746507835],"iteration":433,"passed_time":0.2924344502,"remaining_time":0.04447159842},
{"learn":[0.2746507835],"iteration":434,"passed_time":0.2930084329,"remaining_time":0.04378286928},
{"learn":[0.2746507835],"iteration":435,"passed_time":0.2935811428,"remaining_time":0.04309447968},
{"learn":[0.274651173],"iteration":436,"passed_time":0.2941046123,"remaining_time":0.04239952076},
{"learn":[0.2746515793],"iteration":437,"passed_time":0.2946820912,"remaining_time":0.04171299008},
{"learn":[0.2746477917],"iteration":438,"passed_time":0.2953107869,"remaining_time":0.04103407289},
{"learn":[0.2746459323],"iteration":439,"passed_time":0.2959013973,"remaining_time":0.04035019054},
{"learn":[0.2746407997],"iteration":440,"passed_time":0.2965320776,"remaining_time":0.03967209202},
{"learn":[0.2746330081],"iteration":441,"passed_time":0.2972704379,"remaining_time":0.039008338},
{"learn":[0.2746305438],"iteration":442,"passed_time":0.2981566925,"remaining_time":0.03836327647},
{"learn":[0.274619022],"iteration":443,"passed_time":0.2990455609,"remaining_time":0.03771745813},
{"learn":[0.2746120816],"iteration":444,"passed_time":0.299870364,"remaining_time":0.03706262925},
{"learn":[0.2746049574],"iteration":445,"passed_time":0.3006831573,"remaining_time":0.03640558407},
{"learn":[0.2746048797],"iteration":446,"passed_time":0.3013302182,"remaining_time":0.03572819142},
{"learn":[0.2746047198],"iteration":447,"passed_time":0.3019015568,"remaining_time":0.03504214498},
{"learn":[0.2746049082],"iteration":448,"passed_time":0.3024758278,"remaining_time":0.03435694257},
{"learn":[0.274604701],"iteration":449,"passed_time":0.3031034104,"remaining_time":0.03367815671},
{"learn":[0.2746047076],"iteration":450,"passed_time":0.3036484863,"remaining_time":0.03299063377},
{"learn":[0.274604029],"iteration":451,"passed_time":0.3044089539,"remaining_time":0.03232661457},
{"learn":[0.27460218],"iteration":452,"passed_time":0.3051099297,"remaining_time":0.03165599712},
{"learn":[0.27460218],"iteration":453,"passed_time":0.3057731412,"remaining_time":0.0309814196},
{"learn":[0.27460218],"iteration":454,"passed_time":0.3063344461,"remaining_time":0.03029681335},
{"learn":[0.2746019809],"iteration":455,"passed_time":0.3070570064,"remaining_time":0.02962830763},
{"learn":[0.2746022038],"iteration":456,"passed_time":0.3078089427,"remaining_time":0.0289623294},
{"learn":[0.2746025616],"iteration":457,"passed_time":0.3083583314,"remaining_time":0.02827740157},
{"learn":[0.2746006548],"iteration":458,"passed_time":0.3090179037,"remaining_time":0.02760290643},
{"learn":[0.2745999163],"iteration":459,"passed_time":0.3095542558,"remaining_time":0.02691776137},
{"learn":[0.2745987675],"iteration":460,"passed_time":0.3100918799,"remaining_time":0.02623336945},
{"learn":[0.2745988296],"iteration":461,"passed_time":0.3108006242,"remaining_time":0.02556368771},
{"learn":[0.2745989659],"iteration":462,"passed_time":0.3114054679,"remaining_time":0.02488553415},
{"learn":[0.274597764],"iteration":463,"passed_time":0.3121814453,"remaining_time":0.02422097421},
{"learn":[0.2745975882],"iteration":464,"passed_time":0.3128292114,"remaining_time":0.02354628473},
{"learn":[0.2745968902],"iteration":465,"passed_time":0.3134825181,"remaining_time":0.02287211506},
{"learn":[0.2745931266],"iteration":466,"passed_time":0.3141894813,"remaining_time":0.0222018263},
{"learn":[0.2745933857],"iteration":467,"passed_time":0.3149283122,"remaining_time":0.02153355981},
{"learn":[0.2745928412],"iteration":468,"passed_time":0.3156287037,"remaining_time":0.02086245163},
{"learn":[0.2745926147],"iteration":469,"passed_time":0.3162904438,"remaining_time":0.02018875173},
{"learn":[0.2745912773],"iteration":470,"passed_time":0.3169100978,"remaining_time":0.01951251133},
{"learn":[0.2745856149],"iteration":471,"passed_time":0.3175457139,"remaining_time":0.0188374576},
{"learn":[0.2745804465],"iteration":472,"passed_time":0.3183248569,"remaining_time":0.0181707635},
{"learn":[0.2745810907],"iteration":473,"passed_time":0.3188867156,"remaining_time":0.01749167638},
{"learn":[0.274578745],"iteration":474,"passed_time":0.3197116102,"remaining_time":0.01682692685},
{"learn":[0.2745726835],"iteration":475,"passed_time":0.3205928353,"remaining_time":0.01616434464},
{"learn":[0.2745724133],"iteration":476,"passed_time":0.3211780076,"remaining_time":0.0154865706},
{"learn":[0.274572663],"iteration":477,"passed_time":0.3217766421,"remaining_time":0.01480980361},
{"learn":[0.2745720332],"iteration":478,"passed_time":0.322520217,"remaining_time":0.01413971724},
{"learn":[0.2745722851],"iteration":479,"passed_time":0.3232239491,"remaining_time":0.01346766455},
{"learn":[0.2745724175],"iteration":480,"passed_time":0.323896704,"remaining_time":0.0127942565},
{"learn":[0.2745723852],"iteration":481,"passed_time":0.3244880664,"remaining_time":0.01211781161},
{"learn":[0.2745680399],"iteration":482,"passed_time":0.3252505924,"remaining_time":0.01144774342},
{"learn":[0.2745668187],"iteration":483,"passed_time":0.3258289449,"remaining_time":0.01077120479},
{"learn":[0.2745665455],"iteration":484,"passed_time":0.3263944769,"remaining_time":0.01009467454},
{"learn":[0.2745664367],"iteration":485,"passed_time":0.3269595953,"remaining_time":0.009418589166},
{"learn":[0.2745660927],"iteration":486,"passed_time":0.3274698241,"remaining_time":0.008741494277},
{"learn":[0.2745661804],"iteration":487,"passed_time":0.3280508143,"remaining_time":0.008066823302},
{"learn":[0.2745663861],"iteration":488,"passed_time":0.3287873986,"remaining_time":0.007396035552},
{"learn":[0.2745602207],"iteration":489,"passed_time":0.3294565254,"remaining_time":0.006723602559},
{"learn":[0.274553788],"iteration":490,"passed_time":0.330194774,"remaining_time":0.006052450033},
{"learn":[0.2745542322],"iteration":491,"passed_time":0.3308521586,"remaining_time":0.005379709896},
{"learn":[0.2745509307],"iteration":492,"passed_time":0.3314873821,"remaining_time":0.004706717393},
{"learn":[0.2745507491],"iteration":493,"passed_time":0.33222405,"remaining_time":0.004035109919},
{"learn":[0.2745512901],"iteration":494,"passed_time":0.3327763199,"remaining_time":0.003361376969},
{"learn":[0.2745460921],"iteration":495,"passed_time":0.3335463876,"remaining_time":0.002689890223},
{"learn":[0.2745455396],"iteration":496,"passed_time":0.3340960398,"remaining_time":0.002016676297},
{"learn":[0.2745440034],"iteration":497,"passed_time":0.3346597168,"remaining_time":0.001344014927},
{"learn":[0.2745439316],"iteration":498,"passed_time":0.3352372088,"remaining_time":0.0006718180537},
{"learn":[0.2745439316],"iteration":499,"passed_time":0.3357118931,"remaining_time":0}
]}